listql.py
listql-0.0.1.dev8.dist-info/DESCRIPTION.rst
listql-0.0.1.dev8.dist-info/METADATA
listql-0.0.1.dev8.dist-info/RECORD
listql-0.0.1.dev8.dist-info/WHEEL
listql-0.0.1.dev8.dist-info/metadata.json
listql-0.0.1.dev8.dist-info/pbr.json
listql-0.0.1.dev8.dist-info/top_level.txt
