Metadata-Version: 2.0
Name: listql
Version: 0.0.1.dev8
Summary: Query list like database
Home-page: https://github.com/yujunz/listql
Author: Yujun Zhang
Author-email: zhangyujun@gmail.com
License: MIT
Platform: UNKNOWN
Classifier: Intended Audience :: Developers
Classifier: Natural Language :: English
Classifier: Programming Language :: Python
Classifier: Programming Language :: Python :: 2.7
Classifier: Programming Language :: Python :: 3.4
Classifier: Programming Language :: Python :: 3.5
Requires-Dist: six
